{
  "0": {
    "LHIN Program:  Revenue & Expenses": "Revenue",
    "Budget": null,
    "Budget Adjustments": null,
    "Total": null,
    "YTD Actual": null,
    "Q4 Forecast": null,
    "Q4 $ Forecast Variance to Budget": null,
    "Q4 % Forecast Variance to Budget": null,
    "Comments\nExplanations are required where \nthe Q4 Forecasted % exceeds +/-10%": null
  },
  "1": {
    "LHIN Program:  Revenue & Expenses": "LHIN Global Base Allocation",
    "Budget": 2222638,
    "Budget Adjustments": 0,
    "Total": 2222638,
    "YTD Actual": 1664593,
    "Q4 Forecast": 2222638,
    "Q4 $ Forecast Variance to Budget": 0,
    "Q4 % Forecast Variance to Budget": 0,
    "Comments\nExplanations are required where \nthe Q4 Forecasted % exceeds +/-10%": null
  },
  "2": {
    "LHIN Program:  Revenue & Expenses": "HBAM Funding (CCAC only)",
    "Budget": 0,
    "Budget Adjustments": 0,
    "Total": 0,
    "YTD Actual": 0,
    "Q4 Forecast": 0,
    "Q4 $ Forecast Variance to Budget": 0,
    "Q4 % Forecast Variance to Budget": 0,
    "Comments\nExplanations are required where \nthe Q4 Forecasted % exceeds +/-10%": null
  },
  "3": {
    "LHIN Program:  Revenue & Expenses": "Quality-Based Procedures (CCAC only)",
    "Budget": 0,
    "Budget Adjustments": 0,
    "Total": 0,
    "YTD Actual": 0,
    "Q4 Forecast": 0,
    "Q4 $ Forecast Variance to Budget": 0,
    "Q4 % Forecast Variance to Budget": 0,
    "Comments\nExplanations are required where \nthe Q4 Forecasted % exceeds +/-10%": null
  },
  "4": {
    "LHIN Program:  Revenue & Expenses": "MOHLTC Base Allocation",
    "Budget": 0,
    "Budget Adjustments": 0,
    "Total": 0,
    "YTD Actual": 0,
    "Q4 Forecast": 0,
    "Q4 $ Forecast Variance to Budget": 0,
    "Q4 % Forecast Variance to Budget": 0,
    "Comments\nExplanations are required where \nthe Q4 Forecasted % exceeds +/-10%": null
  },
  "5": {
    "LHIN Program:  Revenue & Expenses": "MOHLTC Other funding envelopes",
    "Budget": 0,
    "Budget Adjustments": 0,
    "Total": 0,
    "YTD Actual": 0,
    "Q4 Forecast": 0,
    "Q4 $ Forecast Variance to Budget": 0,
    "Q4 % Forecast Variance to Budget": 0,
    "Comments\nExplanations are required where \nthe Q4 Forecasted % exceeds +/-10%": null
  },
  "6": {
    "LHIN Program:  Revenue & Expenses": "LHIN One Time",
    "Budget": 0,
    "Budget Adjustments": 0,
    "Total": 0,
    "YTD Actual": 0,
    "Q4 Forecast": 0,
    "Q4 $ Forecast Variance to Budget": 0,
    "Q4 % Forecast Variance to Budget": 0,
    "Comments\nExplanations are required where \nthe Q4 Forecasted % exceeds +/-10%": null
  },
  "7": {
    "LHIN Program:  Revenue & Expenses": "MOHLTC One Time",
    "Budget": 0,
    "Budget Adjustments": 0,
    "Total": 0,
    "YTD Actual": 0,
    "Q4 Forecast": 0,
    "Q4 $ Forecast Variance to Budget": 0,
    "Q4 % Forecast Variance to Budget": 0,
    "Comments\nExplanations are required where \nthe Q4 Forecasted % exceeds +/-10%": null
  },
  "8": {
    "LHIN Program:  Revenue & Expenses": "Paymaster Flow Through (Row 80)",
    "Budget": 0,
    "Budget Adjustments": 0,
    "Total": 0,
    "YTD Actual": 0,
    "Q4 Forecast": 0,
    "Q4 $ Forecast Variance to Budget": 0,
    "Q4 % Forecast Variance to Budget": 0,
    "Comments\nExplanations are required where \nthe Q4 Forecasted % exceeds +/-10%": null
  },
  "9": {
    "LHIN Program:  Revenue & Expenses": "Service Recipient Revenue",
    "Budget": 0,
    "Budget Adjustments": 0,
    "Total": 0,
    "YTD Actual": 0,
    "Q4 Forecast": 0,
    "Q4 $ Forecast Variance to Budget": 0,
    "Q4 % Forecast Variance to Budget": 0,
    "Comments\nExplanations are required where \nthe Q4 Forecasted % exceeds +/-10%": null
  },
  "10": {
    "LHIN Program:  Revenue & Expenses": "Subtotal Revenue LHIN/MOHLTC",
    "Budget": 2222638,
    "Budget Adjustments": 0,
    "Total": 2222638,
    "YTD Actual": 1664593,
    "Q4 Forecast": 2222638,
    "Q4 $ Forecast Variance to Budget": 0,
    "Q4 % Forecast Variance to Budget": 0,
    "Comments\nExplanations are required where \nthe Q4 Forecasted % exceeds +/-10%": null
  },
  "11": {
    "LHIN Program:  Revenue & Expenses": "Recoveries from External/Internal Sources",
    "Budget": 0,
    "Budget Adjustments": 0,
    "Total": 0,
    "YTD Actual": 0,
    "Q4 Forecast": 0,
    "Q4 $ Forecast Variance to Budget": 0,
    "Q4 % Forecast Variance to Budget": 0,
    "Comments\nExplanations are required where \nthe Q4 Forecasted % exceeds +/-10%": null
  },
  "12": {
    "LHIN Program:  Revenue & Expenses": "Donations",
    "Budget": 0,
    "Budget Adjustments": 0,
    "Total": 0,
    "YTD Actual": 0,
    "Q4 Forecast": 0,
    "Q4 $ Forecast Variance to Budget": 0,
    "Q4 % Forecast Variance to Budget": 0,
    "Comments\nExplanations are required where \nthe Q4 Forecasted % exceeds +/-10%": null
  },
  "13": {
    "LHIN Program:  Revenue & Expenses": "Other Funding Sources & Other Revenue",
    "Budget": 0,
    "Budget Adjustments": 0,
    "Total": 0,
    "YTD Actual": 9265,
    "Q4 Forecast": 9265,
    "Q4 $ Forecast Variance to Budget": 9265,
    "Q4 % Forecast Variance to Budget": 0,
    "Comments\nExplanations are required where \nthe Q4 Forecasted % exceeds +/-10%": null
  },
  "14": {
    "LHIN Program:  Revenue & Expenses": "Subtotal Other Revenues",
    "Budget": 0,
    "Budget Adjustments": 0,
    "Total": 0,
    "YTD Actual": 9265,
    "Q4 Forecast": 9265,
    "Q4 $ Forecast Variance to Budget": 9265,
    "Q4 % Forecast Variance to Budget": 0,
    "Comments\nExplanations are required where \nthe Q4 Forecasted % exceeds +/-10%": null
  },
  "15": {
    "LHIN Program:  Revenue & Expenses": "TOTAL REVENUE                               FUND TYPE 2",
    "Budget": 2222638,
    "Budget Adjustments": 0,
    "Total": 2222638,
    "YTD Actual": 1673858,
    "Q4 Forecast": 2231903,
    "Q4 $ Forecast Variance to Budget": 9265,
    "Q4 % Forecast Variance to Budget": 0.0041684701,
    "Comments\nExplanations are required where \nthe Q4 Forecasted % exceeds +/-10%": null
  },
  "16": {
    "LHIN Program:  Revenue & Expenses": "EXPENSES",
    "Budget": null,
    "Budget Adjustments": null,
    "Total": null,
    "YTD Actual": null,
    "Q4 Forecast": null,
    "Q4 $ Forecast Variance to Budget": null,
    "Q4 % Forecast Variance to Budget": null,
    "Comments\nExplanations are required where \nthe Q4 Forecasted % exceeds +/-10%": null
  },
  "17": {
    "LHIN Program:  Revenue & Expenses": "Compensation",
    "Budget": null,
    "Budget Adjustments": null,
    "Total": null,
    "YTD Actual": null,
    "Q4 Forecast": null,
    "Q4 $ Forecast Variance to Budget": null,
    "Q4 % Forecast Variance to Budget": null,
    "Comments\nExplanations are required where \nthe Q4 Forecasted % exceeds +/-10%": null
  },
  "18": {
    "LHIN Program:  Revenue & Expenses": "Salaries (Worked hours + Benefit hours cost) (Row 92+103)",
    "Budget": 1425952,
    "Budget Adjustments": 0,
    "Total": 1425952,
    "YTD Actual": 1093500,
    "Q4 Forecast": 1458000,
    "Q4 $ Forecast Variance to Budget": -32048,
    "Q4 % Forecast Variance to Budget": -0.0224748098,
    "Comments\nExplanations are required where \nthe Q4 Forecasted % exceeds +/-10%": null
  },
  "19": {
    "LHIN Program:  Revenue & Expenses": "Benefit Contributions (Row 93+104)",
    "Budget": 370587,
    "Budget Adjustments": 0,
    "Total": 370587,
    "YTD Actual": 296696,
    "Q4 Forecast": 379600,
    "Q4 $ Forecast Variance to Budget": -9013,
    "Q4 % Forecast Variance to Budget": -0.0243208747,
    "Comments\nExplanations are required where \nthe Q4 Forecasted % exceeds +/-10%": null
  },
  "20": {
    "LHIN Program:  Revenue & Expenses": "Employee Future Benefit Compensation",
    "Budget": 0,
    "Budget Adjustments": 0,
    "Total": 0,
    "YTD Actual": 0,
    "Q4 Forecast": 0,
    "Q4 $ Forecast Variance to Budget": 0,
    "Q4 % Forecast Variance to Budget": 0,
    "Comments\nExplanations are required where \nthe Q4 Forecasted % exceeds +/-10%": null
  },
  "21": {
    "LHIN Program:  Revenue & Expenses": "Physician Compensation (Row 130)",
    "Budget": 113000,
    "Budget Adjustments": 0,
    "Total": 113000,
    "YTD Actual": 82505,
    "Q4 Forecast": 113000,
    "Q4 $ Forecast Variance to Budget": 0,
    "Q4 % Forecast Variance to Budget": 0,
    "Comments\nExplanations are required where \nthe Q4 Forecasted % exceeds +/-10%": null
  },
  "22": {
    "LHIN Program:  Revenue & Expenses": "Physician Assistant Compensation (Row 131)",
    "Budget": 0,
    "Budget Adjustments": 0,
    "Total": 0,
    "YTD Actual": 0,
    "Q4 Forecast": 0,
    "Q4 $ Forecast Variance to Budget": 0,
    "Q4 % Forecast Variance to Budget": 0,
    "Comments\nExplanations are required where \nthe Q4 Forecasted % exceeds +/-10%": null
  },
  "23": {
    "LHIN Program:  Revenue & Expenses": "Nurse Practitioner Compensation  (Row 132)",
    "Budget": 143021,
    "Budget Adjustments": 0,
    "Total": 143021,
    "YTD Actual": 55879,
    "Q4 Forecast": 98303,
    "Q4 $ Forecast Variance to Budget": 44718,
    "Q4 % Forecast Variance to Budget": 0.3126673705,
    "Comments\nExplanations are required where \nthe Q4 Forecasted % exceeds +/-10%": "Partial vacancy during year"
  },
  "24": {
    "LHIN Program:  Revenue & Expenses": "Physiotherapist Compensation (Row 133)",
    "Budget": 0,
    "Budget Adjustments": 0,
    "Total": 0,
    "YTD Actual": 0,
    "Q4 Forecast": 0,
    "Q4 $ Forecast Variance to Budget": 0,
    "Q4 % Forecast Variance to Budget": 0,
    "Comments\nExplanations are required where \nthe Q4 Forecasted % exceeds +/-10%": null
  },
  "25": {
    "LHIN Program:  Revenue & Expenses": "Chiropractor Compensation (Row 134)",
    "Budget": 0,
    "Budget Adjustments": 0,
    "Total": 0,
    "YTD Actual": 0,
    "Q4 Forecast": 0,
    "Q4 $ Forecast Variance to Budget": 0,
    "Q4 % Forecast Variance to Budget": 0,
    "Comments\nExplanations are required where \nthe Q4 Forecasted % exceeds +/-10%": null
  },
  "26": {
    "LHIN Program:  Revenue & Expenses": "All Other Medical Staff Compensation (Row 135)",
    "Budget": 0,
    "Budget Adjustments": 0,
    "Total": 0,
    "YTD Actual": 0,
    "Q4 Forecast": 0,
    "Q4 $ Forecast Variance to Budget": 0,
    "Q4 % Forecast Variance to Budget": 0,
    "Comments\nExplanations are required where \nthe Q4 Forecasted % exceeds +/-10%": null
  },
  "27": {
    "LHIN Program:  Revenue & Expenses": "Sessional Fees",
    "Budget": 0,
    "Budget Adjustments": 0,
    "Total": 0,
    "YTD Actual": 0,
    "Q4 Forecast": 0,
    "Q4 $ Forecast Variance to Budget": 0,
    "Q4 % Forecast Variance to Budget": 0,
    "Comments\nExplanations are required where \nthe Q4 Forecasted % exceeds +/-10%": null
  },
  "28": {
    "LHIN Program:  Revenue & Expenses": "Service Costs",
    "Budget": null,
    "Budget Adjustments": null,
    "Total": null,
    "YTD Actual": null,
    "Q4 Forecast": null,
    "Q4 $ Forecast Variance to Budget": null,
    "Q4 % Forecast Variance to Budget": null,
    "Comments\nExplanations are required where \nthe Q4 Forecasted % exceeds +/-10%": null
  },
  "29": {
    "LHIN Program:  Revenue & Expenses": "Med/Surgical Supplies & Drugs",
    "Budget": 0,
    "Budget Adjustments": 0,
    "Total": 0,
    "YTD Actual": 0,
    "Q4 Forecast": 0,
    "Q4 $ Forecast Variance to Budget": 0,
    "Q4 % Forecast Variance to Budget": 0,
    "Comments\nExplanations are required where \nthe Q4 Forecasted % exceeds +/-10%": null
  },
  "30": {
    "LHIN Program:  Revenue & Expenses": "Supplies & Sundry Expenses",
    "Budget": 170078,
    "Budget Adjustments": 0,
    "Total": 170078,
    "YTD Actual": 145278,
    "Q4 Forecast": 183000,
    "Q4 $ Forecast Variance to Budget": -12922,
    "Q4 % Forecast Variance to Budget": -0.0759769047,
    "Comments\nExplanations are required where \nthe Q4 Forecasted % exceeds +/-10%": null
  },
  "31": {
    "LHIN Program:  Revenue & Expenses": "Community One Time Expense",
    "Budget": 0,
    "Budget Adjustments": 0,
    "Total": 0,
    "YTD Actual": 0,
    "Q4 Forecast": 0,
    "Q4 $ Forecast Variance to Budget": 0,
    "Q4 % Forecast Variance to Budget": 0,
    "Comments\nExplanations are required where \nthe Q4 Forecasted % exceeds +/-10%": null
  },
  "32": {
    "LHIN Program:  Revenue & Expenses": "Equipment Expenses",
    "Budget": 0,
    "Budget Adjustments": 0,
    "Total": 0,
    "YTD Actual": 0,
    "Q4 Forecast": 0,
    "Q4 $ Forecast Variance to Budget": 0,
    "Q4 % Forecast Variance to Budget": 0,
    "Comments\nExplanations are required where \nthe Q4 Forecasted % exceeds +/-10%": null
  },
  "33": {
    "LHIN Program:  Revenue & Expenses": "Amortization on Major Equip, Software License & Fees",
    "Budget": 0,
    "Budget Adjustments": 0,
    "Total": 0,
    "YTD Actual": 0,
    "Q4 Forecast": 0,
    "Q4 $ Forecast Variance to Budget": 0,
    "Q4 % Forecast Variance to Budget": 0,
    "Comments\nExplanations are required where \nthe Q4 Forecasted % exceeds +/-10%": null
  },
  "34": {
    "LHIN Program:  Revenue & Expenses": "Contracted Out Expense",
    "Budget": 0,
    "Budget Adjustments": 0,
    "Total": 0,
    "YTD Actual": 0,
    "Q4 Forecast": 0,
    "Q4 $ Forecast Variance to Budget": 0,
    "Q4 % Forecast Variance to Budget": 0,
    "Comments\nExplanations are required where \nthe Q4 Forecasted % exceeds +/-10%": null
  },
  "35": {
    "LHIN Program:  Revenue & Expenses": "Buildings & Grounds Expenses",
    "Budget": 0,
    "Budget Adjustments": 0,
    "Total": 0,
    "YTD Actual": 0,
    "Q4 Forecast": 0,
    "Q4 $ Forecast Variance to Budget": 0,
    "Q4 % Forecast Variance to Budget": 0,
    "Comments\nExplanations are required where \nthe Q4 Forecasted % exceeds +/-10%": null
  },
  "36": {
    "LHIN Program:  Revenue & Expenses": "Building Amortization",
    "Budget": 0,
    "Budget Adjustments": 0,
    "Total": 0,
    "YTD Actual": 0,
    "Q4 Forecast": 0,
    "Q4 $ Forecast Variance to Budget": 0,
    "Q4 % Forecast Variance to Budget": 0,
    "Comments\nExplanations are required where \nthe Q4 Forecasted % exceeds +/-10%": null
  },
  "37": {
    "LHIN Program:  Revenue & Expenses": "TOTAL EXPENSES                               FUND TYPE 2",
    "Budget": 2222638,
    "Budget Adjustments": 0,
    "Total": 2222638,
    "YTD Actual": 1673858,
    "Q4 Forecast": 2231903,
    "Q4 $ Forecast Variance to Budget": -9265,
    "Q4 % Forecast Variance to Budget": -0.0041684701,
    "Comments\nExplanations are required where \nthe Q4 Forecasted % exceeds +/-10%": null
  },
  "38": {
    "LHIN Program:  Revenue & Expenses": "NET SURPLUS/(DEFICIT) FROM OPERATIONS",
    "Budget": 0,
    "Budget Adjustments": 0,
    "Total": 0,
    "YTD Actual": 0,
    "Q4 Forecast": 0,
    "Q4 $ Forecast Variance to Budget": 0,
    "Q4 % Forecast Variance to Budget": 0,
    "Comments\nExplanations are required where \nthe Q4 Forecasted % exceeds +/-10%": null
  },
  "39": {
    "LHIN Program:  Revenue & Expenses": "Amortization - Grants/Donations Revenue",
    "Budget": 0,
    "Budget Adjustments": 0,
    "Total": 0,
    "YTD Actual": 0,
    "Q4 Forecast": 0,
    "Q4 $ Forecast Variance to Budget": 0,
    "Q4 % Forecast Variance to Budget": 0,
    "Comments\nExplanations are required where \nthe Q4 Forecasted % exceeds +/-10%": null
  },
  "40": {
    "LHIN Program:  Revenue & Expenses": "SURPLUS/DEFICIT Incl. Amortization of Grants/Donations",
    "Budget": 0,
    "Budget Adjustments": 0,
    "Total": 0,
    "YTD Actual": 0,
    "Q4 Forecast": 0,
    "Q4 $ Forecast Variance to Budget": 0,
    "Q4 % Forecast Variance to Budget": 0,
    "Comments\nExplanations are required where \nthe Q4 Forecasted % exceeds +/-10%": null
  },
  "41": {
    "LHIN Program:  Revenue & Expenses": "FUND TYPE 3 - OTHER",
    "Budget": null,
    "Budget Adjustments": null,
    "Total": null,
    "YTD Actual": null,
    "Q4 Forecast": null,
    "Q4 $ Forecast Variance to Budget": null,
    "Q4 % Forecast Variance to Budget": null,
    "Comments\nExplanations are required where \nthe Q4 Forecasted % exceeds +/-10%": null
  },
  "42": {
    "LHIN Program:  Revenue & Expenses": "Total Revenue (Type 3)",
    "Budget": 0,
    "Budget Adjustments": 0,
    "Total": 0,
    "YTD Actual": 0,
    "Q4 Forecast": 0,
    "Q4 $ Forecast Variance to Budget": 0,
    "Q4 % Forecast Variance to Budget": 0,
    "Comments\nExplanations are required where \nthe Q4 Forecasted % exceeds +/-10%": null
  },
  "43": {
    "LHIN Program:  Revenue & Expenses": "Total Expenses (Type 3)",
    "Budget": 0,
    "Budget Adjustments": 0,
    "Total": 0,
    "YTD Actual": 0,
    "Q4 Forecast": 0,
    "Q4 $ Forecast Variance to Budget": 0,
    "Q4 % Forecast Variance to Budget": 0,
    "Comments\nExplanations are required where \nthe Q4 Forecasted % exceeds +/-10%": null
  },
  "44": {
    "LHIN Program:  Revenue & Expenses": "NET SURPLUS/(DEFICIT)                     FUND TYPE 3",
    "Budget": 0,
    "Budget Adjustments": 0,
    "Total": 0,
    "YTD Actual": 0,
    "Q4 Forecast": 0,
    "Q4 $ Forecast Variance to Budget": 0,
    "Q4 % Forecast Variance to Budget": 0,
    "Comments\nExplanations are required where \nthe Q4 Forecasted % exceeds +/-10%": null
  },
  "45": {
    "LHIN Program:  Revenue & Expenses": "FUND TYPE 1 - HOSPITAL",
    "Budget": null,
    "Budget Adjustments": null,
    "Total": null,
    "YTD Actual": null,
    "Q4 Forecast": null,
    "Q4 $ Forecast Variance to Budget": null,
    "Q4 % Forecast Variance to Budget": null,
    "Comments\nExplanations are required where \nthe Q4 Forecasted % exceeds +/-10%": null
  },
  "46": {
    "LHIN Program:  Revenue & Expenses": "Total Revenue (Type 1)",
    "Budget": 0,
    "Budget Adjustments": 0,
    "Total": 0,
    "YTD Actual": 0,
    "Q4 Forecast": 0,
    "Q4 $ Forecast Variance to Budget": 0,
    "Q4 % Forecast Variance to Budget": 0,
    "Comments\nExplanations are required where \nthe Q4 Forecasted % exceeds +/-10%": null
  },
  "47": {
    "LHIN Program:  Revenue & Expenses": "Total Expenses (Type 1)",
    "Budget": 0,
    "Budget Adjustments": 0,
    "Total": 0,
    "YTD Actual": 0,
    "Q4 Forecast": 0,
    "Q4 $ Forecast Variance to Budget": 0,
    "Q4 % Forecast Variance to Budget": 0,
    "Comments\nExplanations are required where \nthe Q4 Forecasted % exceeds +/-10%": null
  },
  "48": {
    "LHIN Program:  Revenue & Expenses": "NET SURPLUS/(DEFICIT)                     FUND TYPE 1",
    "Budget": 0,
    "Budget Adjustments": 0,
    "Total": 0,
    "YTD Actual": 0,
    "Q4 Forecast": 0,
    "Q4 $ Forecast Variance to Budget": 0,
    "Q4 % Forecast Variance to Budget": 0,
    "Comments\nExplanations are required where \nthe Q4 Forecasted % exceeds +/-10%": null
  },
  "49": {
    "LHIN Program:  Revenue & Expenses": "ALL FUND TYPES",
    "Budget": null,
    "Budget Adjustments": null,
    "Total": null,
    "YTD Actual": null,
    "Q4 Forecast": null,
    "Q4 $ Forecast Variance to Budget": null,
    "Q4 % Forecast Variance to Budget": null,
    "Comments\nExplanations are required where \nthe Q4 Forecasted % exceeds +/-10%": null
  },
  "50": {
    "LHIN Program:  Revenue & Expenses": "Total Revenue (All Funds)",
    "Budget": 2222638,
    "Budget Adjustments": 0,
    "Total": 2222638,
    "YTD Actual": 1673858,
    "Q4 Forecast": 2231903,
    "Q4 $ Forecast Variance to Budget": 9265,
    "Q4 % Forecast Variance to Budget": 0.0041684701,
    "Comments\nExplanations are required where \nthe Q4 Forecasted % exceeds +/-10%": null
  },
  "51": {
    "LHIN Program:  Revenue & Expenses": "Total Expenses (All Funds)",
    "Budget": 2222638,
    "Budget Adjustments": 0,
    "Total": 2222638,
    "YTD Actual": 1673858,
    "Q4 Forecast": 2231903,
    "Q4 $ Forecast Variance to Budget": -9265,
    "Q4 % Forecast Variance to Budget": -0.0041684701,
    "Comments\nExplanations are required where \nthe Q4 Forecasted % exceeds +/-10%": null
  },
  "52": {
    "LHIN Program:  Revenue & Expenses": "NET SURPLUS/(DEFICIT)                     ALL FUND TYPES",
    "Budget": 0,
    "Budget Adjustments": 0,
    "Total": 0,
    "YTD Actual": 0,
    "Q4 Forecast": 0,
    "Q4 $ Forecast Variance to Budget": 0,
    "Q4 % Forecast Variance to Budget": 0,
    "Comments\nExplanations are required where \nthe Q4 Forecasted % exceeds +/-10%": null
  },
  "53": {
    "LHIN Program:  Revenue & Expenses": "Total Admin Expenses  Allocated to the TPBEs",
    "Budget": null,
    "Budget Adjustments": null,
    "Total": null,
    "YTD Actual": null,
    "Q4 Forecast": null,
    "Q4 $ Forecast Variance to Budget": null,
    "Q4 % Forecast Variance to Budget": null,
    "Comments\nExplanations are required where \nthe Q4 Forecasted % exceeds +/-10%": null
  },
  "54": {
    "LHIN Program:  Revenue & Expenses": "Undistributed Accounting Centres",
    "Budget": 0,
    "Budget Adjustments": 0,
    "Total": 0,
    "YTD Actual": 0,
    "Q4 Forecast": 0,
    "Q4 $ Forecast Variance to Budget": 0,
    "Q4 % Forecast Variance to Budget": 0,
    "Comments\nExplanations are required where \nthe Q4 Forecasted % exceeds +/-10%": null
  },
  "55": {
    "LHIN Program:  Revenue & Expenses": "Plant Operations",
    "Budget": 0,
    "Budget Adjustments": 0,
    "Total": 0,
    "YTD Actual": 0,
    "Q4 Forecast": 0,
    "Q4 $ Forecast Variance to Budget": 0,
    "Q4 % Forecast Variance to Budget": 0,
    "Comments\nExplanations are required where \nthe Q4 Forecasted % exceeds +/-10%": null
  },
  "56": {
    "LHIN Program:  Revenue & Expenses": "Volunteer Services",
    "Budget": 0,
    "Budget Adjustments": 0,
    "Total": 0,
    "YTD Actual": 0,
    "Q4 Forecast": 0,
    "Q4 $ Forecast Variance to Budget": 0,
    "Q4 % Forecast Variance to Budget": 0,
    "Comments\nExplanations are required where \nthe Q4 Forecasted % exceeds +/-10%": null
  },
  "57": {
    "LHIN Program:  Revenue & Expenses": "Information Systems Support",
    "Budget": 0,
    "Budget Adjustments": 0,
    "Total": 0,
    "YTD Actual": 0,
    "Q4 Forecast": 0,
    "Q4 $ Forecast Variance to Budget": 0,
    "Q4 % Forecast Variance to Budget": 0,
    "Comments\nExplanations are required where \nthe Q4 Forecasted % exceeds +/-10%": null
  },
  "58": {
    "LHIN Program:  Revenue & Expenses": "General Administration",
    "Budget": 109557,
    "Budget Adjustments": 0,
    "Total": 109557,
    "YTD Actual": 81783,
    "Q4 Forecast": 111557,
    "Q4 $ Forecast Variance to Budget": -2000,
    "Q4 % Forecast Variance to Budget": -0.0182553374,
    "Comments\nExplanations are required where \nthe Q4 Forecasted % exceeds +/-10%": null
  },
  "59": {
    "LHIN Program:  Revenue & Expenses": "Other Administrative Expense",
    "Budget": 0,
    "Budget Adjustments": 0,
    "Total": 0,
    "YTD Actual": 0,
    "Q4 Forecast": 0,
    "Q4 $ Forecast Variance to Budget": 0,
    "Q4 % Forecast Variance to Budget": 0,
    "Comments\nExplanations are required where \nthe Q4 Forecasted % exceeds +/-10%": null
  },
  "60": {
    "LHIN Program:  Revenue & Expenses": "Admin & Support Services",
    "Budget": 109557,
    "Budget Adjustments": 0,
    "Total": 109557,
    "YTD Actual": 81783,
    "Q4 Forecast": 111557,
    "Q4 $ Forecast Variance to Budget": -2000,
    "Q4 % Forecast Variance to Budget": -0.0182553374,
    "Comments\nExplanations are required where \nthe Q4 Forecasted % exceeds +/-10%": null
  },
  "61": {
    "LHIN Program:  Revenue & Expenses": "Management Clinical Services",
    "Budget": 0,
    "Budget Adjustments": 0,
    "Total": 0,
    "YTD Actual": 0,
    "Q4 Forecast": 0,
    "Q4 $ Forecast Variance to Budget": 0,
    "Q4 % Forecast Variance to Budget": 0,
    "Comments\nExplanations are required where \nthe Q4 Forecasted % exceeds +/-10%": null
  },
  "62": {
    "LHIN Program:  Revenue & Expenses": "Medical Resources",
    "Budget": 0,
    "Budget Adjustments": 0,
    "Total": 0,
    "YTD Actual": 0,
    "Q4 Forecast": 0,
    "Q4 $ Forecast Variance to Budget": 0,
    "Q4 % Forecast Variance to Budget": 0,
    "Comments\nExplanations are required where \nthe Q4 Forecasted % exceeds +/-10%": null
  },
  "63": {
    "LHIN Program:  Revenue & Expenses": "Total Admin & Undistributed Expenses",
    "Budget": 109557,
    "Budget Adjustments": 0,
    "Total": 109557,
    "YTD Actual": 81783,
    "Q4 Forecast": 111557,
    "Q4 $ Forecast Variance to Budget": -2000,
    "Q4 % Forecast Variance to Budget": -0.0182553374,
    "Comments\nExplanations are required where \nthe Q4 Forecasted % exceeds +/-10%": null
  },
  "64": {
    "LHIN Program:  Revenue & Expenses": "PAYMASTER AGREEMENTS",
    "Budget": null,
    "Budget Adjustments": null,
    "Total": null,
    "YTD Actual": null,
    "Q4 Forecast": null,
    "Q4 $ Forecast Variance to Budget": null,
    "Q4 % Forecast Variance to Budget": null,
    "Comments\nExplanations are required where \nthe Q4 Forecasted % exceeds +/-10%": null
  },
  "65": {
    "LHIN Program:  Revenue & Expenses": "Enter details here",
    "Budget": 0,
    "Budget Adjustments": 0,
    "Total": 0,
    "YTD Actual": 0,
    "Q4 Forecast": 0,
    "Q4 $ Forecast Variance to Budget": 0,
    "Q4 % Forecast Variance to Budget": 0,
    "Comments\nExplanations are required where \nthe Q4 Forecasted % exceeds +/-10%": null
  },
  "66": {
    "LHIN Program:  Revenue & Expenses": "Enter details here",
    "Budget": 0,
    "Budget Adjustments": 0,
    "Total": 0,
    "YTD Actual": 0,
    "Q4 Forecast": 0,
    "Q4 $ Forecast Variance to Budget": 0,
    "Q4 % Forecast Variance to Budget": 0,
    "Comments\nExplanations are required where \nthe Q4 Forecasted % exceeds +/-10%": null
  },
  "67": {
    "LHIN Program:  Revenue & Expenses": "Enter details here",
    "Budget": 0,
    "Budget Adjustments": 0,
    "Total": 0,
    "YTD Actual": 0,
    "Q4 Forecast": 0,
    "Q4 $ Forecast Variance to Budget": 0,
    "Q4 % Forecast Variance to Budget": 0,
    "Comments\nExplanations are required where \nthe Q4 Forecasted % exceeds +/-10%": null
  },
  "68": {
    "LHIN Program:  Revenue & Expenses": "Enter details here",
    "Budget": 0,
    "Budget Adjustments": 0,
    "Total": 0,
    "YTD Actual": 0,
    "Q4 Forecast": 0,
    "Q4 $ Forecast Variance to Budget": 0,
    "Q4 % Forecast Variance to Budget": 0,
    "Comments\nExplanations are required where \nthe Q4 Forecasted % exceeds +/-10%": null
  },
  "69": {
    "LHIN Program:  Revenue & Expenses": "Enter details here",
    "Budget": 0,
    "Budget Adjustments": 0,
    "Total": 0,
    "YTD Actual": 0,
    "Q4 Forecast": 0,
    "Q4 $ Forecast Variance to Budget": 0,
    "Q4 % Forecast Variance to Budget": 0,
    "Comments\nExplanations are required where \nthe Q4 Forecasted % exceeds +/-10%": null
  },
  "70": {
    "LHIN Program:  Revenue & Expenses": "Enter details here",
    "Budget": 0,
    "Budget Adjustments": 0,
    "Total": 0,
    "YTD Actual": 0,
    "Q4 Forecast": 0,
    "Q4 $ Forecast Variance to Budget": 0,
    "Q4 % Forecast Variance to Budget": 0,
    "Comments\nExplanations are required where \nthe Q4 Forecasted % exceeds +/-10%": null
  },
  "71": {
    "LHIN Program:  Revenue & Expenses": "Total Paymaster/Flow Through (transfers to line 18 above)",
    "Budget": 0,
    "Budget Adjustments": 0,
    "Total": 0,
    "YTD Actual": 0,
    "Q4 Forecast": 0,
    "Q4 $ Forecast Variance to Budget": 0,
    "Q4 % Forecast Variance to Budget": 0,
    "Comments\nExplanations are required where \nthe Q4 Forecasted % exceeds +/-10%": null
  },
  "72": {
    "LHIN Program:  Revenue & Expenses": "GLOBAL INDICATORS",
    "Budget": null,
    "Budget Adjustments": null,
    "Total": null,
    "YTD Actual": null,
    "Q4 Forecast": null,
    "Q4 $ Forecast Variance to Budget": null,
    "Q4 % Forecast Variance to Budget": null,
    "Comments\nExplanations are required where \nthe Q4 Forecasted % exceeds +/-10%": null
  },
  "73": {
    "LHIN Program:  Revenue & Expenses": "% Non-LHIN/MOHLTC Global Revenue (Fund Type 2 only)",
    "Budget": 0,
    "Budget Adjustments": 0,
    "Total": 0,
    "YTD Actual": 0.0055351171,
    "Q4 Forecast": 0.0041511661,
    "Q4 $ Forecast Variance to Budget": 0.0041511661,
    "Q4 % Forecast Variance to Budget": 0,
    "Comments\nExplanations are required where \nthe Q4 Forecasted % exceeds +/-10%": null
  },
  "74": {
    "LHIN Program:  Revenue & Expenses": "% Fund Type 2 Expenses Spent on Admin & Support",
    "Budget": 0.0492914276,
    "Budget Adjustments": 0,
    "Total": 0.0492914276,
    "YTD Actual": 0.0488589833,
    "Q4 Forecast": 0.049982907,
    "Q4 $ Forecast Variance to Budget": -0.0006914794,
    "Q4 % Forecast Variance to Budget": -0.0140283904,
    "Comments\nExplanations are required where \nthe Q4 Forecasted % exceeds +/-10%": null
  },
  "75": {
    "LHIN Program:  Revenue & Expenses": "% Fund Type 2 Expenses Spent on Admin (Total)",
    "Budget": 0.0492914276,
    "Budget Adjustments": 0,
    "Total": 0.0492914276,
    "YTD Actual": 0.0488589833,
    "Q4 Forecast": 0.049982907,
    "Q4 $ Forecast Variance to Budget": -0.0006914794,
    "Q4 % Forecast Variance to Budget": -0.0140283904,
    "Comments\nExplanations are required where \nthe Q4 Forecasted % exceeds +/-10%": null
  },
  "76": {
    "LHIN Program:  Revenue & Expenses": "% Total Benefits / Total Compensation (incl. ben. contr.)",
    "Budget": 0.206278294,
    "Budget Adjustments": 0,
    "Total": 0.206278294,
    "YTD Actual": 0.2134202659,
    "Q4 Forecast": 0.2065737919,
    "Q4 $ Forecast Variance to Budget": -0.0002954979,
    "Q4 % Forecast Variance to Budget": -0.0014325207,
    "Comments\nExplanations are required where \nthe Q4 Forecasted % exceeds +/-10%": null
  },
  "77": {
    "LHIN Program:  Revenue & Expenses": "% Total Compensation (MOS & UPP) / Total Expenses ",
    "Budget": 0.8082913187,
    "Budget Adjustments": 0,
    "Total": 0.8082913187,
    "YTD Actual": 0.8305340118,
    "Q4 Forecast": 0.8233332721,
    "Q4 $ Forecast Variance to Budget": -0.0150419534,
    "Q4 % Forecast Variance to Budget": -0.0186095694,
    "Comments\nExplanations are required where \nthe Q4 Forecasted % exceeds +/-10%": null
  },
  "78": {
    "LHIN Program:  Revenue & Expenses": null,
    "Budget": null,
    "Budget Adjustments": null,
    "Total": null,
    "YTD Actual": null,
    "Q4 Forecast": null,
    "Q4 $ Forecast Variance to Budget": null,
    "Q4 % Forecast Variance to Budget": null,
    "Comments\nExplanations are required where \nthe Q4 Forecasted % exceeds +/-10%": null
  },
  "79": {
    "LHIN Program:  Revenue & Expenses": "LHIN Program:  FTE Planning",
    "Budget": null,
    "Budget Adjustments": null,
    "Total": null,
    "YTD Actual": null,
    "Q4 Forecast": null,
    "Q4 $ Forecast Variance to Budget": null,
    "Q4 % Forecast Variance to Budget": null,
    "Comments\nExplanations are required where \nthe Q4 Forecasted % exceeds +/-10%": null
  },
  "80": {
    "LHIN Program:  Revenue & Expenses": "721 FTE- Administration and Support Services",
    "Budget": null,
    "Budget Adjustments": null,
    "Total": null,
    "YTD Actual": null,
    "Q4 Forecast": null,
    "Q4 $ Forecast Variance to Budget": null,
    "Q4 % Forecast Variance to Budget": null,
    "Comments\nExplanations are required where \nthe Q4 Forecasted % exceeds +/-10%": null
  },
  "81": {
    "LHIN Program:  Revenue & Expenses": "MOS FTE - Admin & Support",
    "Budget": 0,
    "Budget Adjustments": 0,
    "Total": 0,
    "YTD Actual": 0,
    "Q4 Forecast": 0,
    "Q4 $ Forecast Variance to Budget": 0,
    "Q4 % Forecast Variance to Budget": 0,
    "Comments\nExplanations are required where \nthe Q4 Forecasted % exceeds +/-10%": null
  },
  "82": {
    "LHIN Program:  Revenue & Expenses": "UPP  FTE - Admin & Support",
    "Budget": 0,
    "Budget Adjustments": 0,
    "Total": 0,
    "YTD Actual": 0,
    "Q4 Forecast": 0,
    "Q4 $ Forecast Variance to Budget": 0,
    "Q4 % Forecast Variance to Budget": 0,
    "Comments\nExplanations are required where \nthe Q4 Forecasted % exceeds +/-10%": null
  },
  "83": {
    "LHIN Program:  Revenue & Expenses": "Salaries (Worked hours + Benefit hours cost) - Admin & Support",
    "Budget": 0,
    "Budget Adjustments": 0,
    "Total": 0,
    "YTD Actual": 0,
    "Q4 Forecast": 0,
    "Q4 $ Forecast Variance to Budget": 0,
    "Q4 % Forecast Variance to Budget": 0,
    "Comments\nExplanations are required where \nthe Q4 Forecasted % exceeds +/-10%": null
  },
  "84": {
    "LHIN Program:  Revenue & Expenses": "Benefit Contributions - Admin & Support",
    "Budget": 0,
    "Budget Adjustments": 0,
    "Total": 0,
    "YTD Actual": 0,
    "Q4 Forecast": 0,
    "Q4 $ Forecast Variance to Budget": 0,
    "Q4 % Forecast Variance to Budget": 0,
    "Comments\nExplanations are required where \nthe Q4 Forecasted % exceeds +/-10%": null
  },
  "85": {
    "LHIN Program:  Revenue & Expenses": "# of Volunteers - Admin & Support",
    "Budget": 0,
    "Budget Adjustments": 0,
    "Total": 0,
    "YTD Actual": 0,
    "Q4 Forecast": 0,
    "Q4 $ Forecast Variance to Budget": 0,
    "Q4 % Forecast Variance to Budget": 0,
    "Comments\nExplanations are required where \nthe Q4 Forecasted % exceeds +/-10%": null
  },
  "86": {
    "LHIN Program:  Revenue & Expenses": "Volunteer Hours - Admin & Support",
    "Budget": 0,
    "Budget Adjustments": 0,
    "Total": 0,
    "YTD Actual": 0,
    "Q4 Forecast": 0,
    "Q4 $ Forecast Variance to Budget": 0,
    "Q4 % Forecast Variance to Budget": 0,
    "Comments\nExplanations are required where \nthe Q4 Forecasted % exceeds +/-10%": null
  },
  "87": {
    "LHIN Program:  Revenue & Expenses": "Total Admin & Support Services FTE",
    "Budget": 0,
    "Budget Adjustments": 0,
    "Total": 0,
    "YTD Actual": 0,
    "Q4 Forecast": 0,
    "Q4 $ Forecast Variance to Budget": 0,
    "Q4 % Forecast Variance to Budget": 0,
    "Comments\nExplanations are required where \nthe Q4 Forecasted % exceeds +/-10%": null
  },
  "88": {
    "LHIN Program:  Revenue & Expenses": "Total Admin & Support Services Total Compensation",
    "Budget": 0,
    "Budget Adjustments": 0,
    "Total": 0,
    "YTD Actual": 0,
    "Q4 Forecast": 0,
    "Q4 $ Forecast Variance to Budget": 0,
    "Q4 % Forecast Variance to Budget": 0,
    "Comments\nExplanations are required where \nthe Q4 Forecasted % exceeds +/-10%": null
  },
  "89": {
    "LHIN Program:  Revenue & Expenses": "Average Cost per Admin & Support Services FTE",
    "Budget": 0,
    "Budget Adjustments": 0,
    "Total": 0,
    "YTD Actual": 0,
    "Q4 Forecast": 0,
    "Q4 $ Forecast Variance to Budget": 0,
    "Q4 % Forecast Variance to Budget": 0,
    "Comments\nExplanations are required where \nthe Q4 Forecasted % exceeds +/-10%": null
  },
  "90": {
    "LHIN Program:  Revenue & Expenses": "Admin & Support Services VH as % of Total FTE",
    "Budget": 0,
    "Budget Adjustments": 0,
    "Total": 0,
    "YTD Actual": 0,
    "Q4 Forecast": 0,
    "Q4 $ Forecast Variance to Budget": 0,
    "Q4 % Forecast Variance to Budget": 0,
    "Comments\nExplanations are required where \nthe Q4 Forecasted % exceeds +/-10%": null
  },
  "91": {
    "LHIN Program:  Revenue & Expenses": "725 FTE- Direct Services",
    "Budget": null,
    "Budget Adjustments": null,
    "Total": null,
    "YTD Actual": null,
    "Q4 Forecast": null,
    "Q4 $ Forecast Variance to Budget": null,
    "Q4 % Forecast Variance to Budget": null,
    "Comments\nExplanations are required where \nthe Q4 Forecasted % exceeds +/-10%": null
  },
  "92": {
    "LHIN Program:  Revenue & Expenses": "MOS FTE - Direct",
    "Budget": 4.52,
    "Budget Adjustments": 0,
    "Total": 4.52,
    "YTD Actual": 4.15,
    "Q4 Forecast": 4.3,
    "Q4 $ Forecast Variance to Budget": 0.22,
    "Q4 % Forecast Variance to Budget": 0.0486725664,
    "Comments\nExplanations are required where \nthe Q4 Forecasted % exceeds +/-10%": null
  },
  "93": {
    "LHIN Program:  Revenue & Expenses": "UPP  FTE - Direct",
    "Budget": 13.16,
    "Budget Adjustments": 0,
    "Total": 13.16,
    "YTD Actual": 13.89,
    "Q4 Forecast": 13.5,
    "Q4 $ Forecast Variance to Budget": -0.34,
    "Q4 % Forecast Variance to Budget": -0.0258358663,
    "Comments\nExplanations are required where \nthe Q4 Forecasted % exceeds +/-10%": null
  },
  "94": {
    "LHIN Program:  Revenue & Expenses": "Salaries (Worked hours + Benefit hours cost) - Direct",
    "Budget": 1425952,
    "Budget Adjustments": 0,
    "Total": 1425952,
    "YTD Actual": 1093500,
    "Q4 Forecast": 1458000,
    "Q4 $ Forecast Variance to Budget": -32048,
    "Q4 % Forecast Variance to Budget": -0.0224748098,
    "Comments\nExplanations are required where \nthe Q4 Forecasted % exceeds +/-10%": null
  },
  "95": {
    "LHIN Program:  Revenue & Expenses": "Benefit Contributions - Direct",
    "Budget": 370587,
    "Budget Adjustments": 0,
    "Total": 370587,
    "YTD Actual": 296696,
    "Q4 Forecast": 379600,
    "Q4 $ Forecast Variance to Budget": -9013,
    "Q4 % Forecast Variance to Budget": -0.0243208747,
    "Comments\nExplanations are required where \nthe Q4 Forecasted % exceeds +/-10%": null
  },
  "96": {
    "LHIN Program:  Revenue & Expenses": "# of Volunteers - Direct",
    "Budget": 0,
    "Budget Adjustments": 0,
    "Total": 0,
    "YTD Actual": 0,
    "Q4 Forecast": 0,
    "Q4 $ Forecast Variance to Budget": 0,
    "Q4 % Forecast Variance to Budget": 0,
    "Comments\nExplanations are required where \nthe Q4 Forecasted % exceeds +/-10%": null
  },
  "97": {
    "LHIN Program:  Revenue & Expenses": "Volunteer Hours - Direct",
    "Budget": 0,
    "Budget Adjustments": 0,
    "Total": 0,
    "YTD Actual": 0,
    "Q4 Forecast": 0,
    "Q4 $ Forecast Variance to Budget": 0,
    "Q4 % Forecast Variance to Budget": 0,
    "Comments\nExplanations are required where \nthe Q4 Forecasted % exceeds +/-10%": null
  },
  "98": {
    "LHIN Program:  Revenue & Expenses": "Total Direct Services FTE",
    "Budget": 17.68,
    "Budget Adjustments": 0,
    "Total": 17.68,
    "YTD Actual": 18.04,
    "Q4 Forecast": 17.8,
    "Q4 $ Forecast Variance to Budget": -0.12,
    "Q4 % Forecast Variance to Budget": -0.0067873303,
    "Comments\nExplanations are required where \nthe Q4 Forecasted % exceeds +/-10%": null
  },
  "99": {
    "LHIN Program:  Revenue & Expenses": "Total Direct Services Total Compensation",
    "Budget": 1796539,
    "Budget Adjustments": 0,
    "Total": 1796539,
    "YTD Actual": 1390196,
    "Q4 Forecast": 1837600,
    "Q4 $ Forecast Variance to Budget": -41061,
    "Q4 % Forecast Variance to Budget": -0.0228556129,
    "Comments\nExplanations are required where \nthe Q4 Forecasted % exceeds +/-10%": null
  },
  "100": {
    "LHIN Program:  Revenue & Expenses": "Average Cost Per Direct Servicers FTE",
    "Budget": 101614.1968325792,
    "Budget Adjustments": 0,
    "Total": 101614.1968325792,
    "YTD Actual": 77061.8625277162,
    "Q4 Forecast": 103235.9550561798,
    "Q4 $ Forecast Variance to Budget": -1621.7582236006,
    "Q4 % Forecast Variance to Budget": -0.0159599571,
    "Comments\nExplanations are required where \nthe Q4 Forecasted % exceeds +/-10%": null
  },
  "101": {
    "LHIN Program:  Revenue & Expenses": "Direct Services VH as % of Total FTE",
    "Budget": 0,
    "Budget Adjustments": 0,
    "Total": 0,
    "YTD Actual": 0,
    "Q4 Forecast": 0,
    "Q4 $ Forecast Variance to Budget": 0,
    "Q4 % Forecast Variance to Budget": 0,
    "Comments\nExplanations are required where \nthe Q4 Forecasted % exceeds +/-10%": null
  },
  "102": {
    "LHIN Program:  Revenue & Expenses": "FTE- Medical Staff Remuneration",
    "Budget": null,
    "Budget Adjustments": null,
    "Total": null,
    "YTD Actual": null,
    "Q4 Forecast": null,
    "Q4 $ Forecast Variance to Budget": null,
    "Q4 % Forecast Variance to Budget": null,
    "Comments\nExplanations are required where \nthe Q4 Forecasted % exceeds +/-10%": null
  },
  "103": {
    "LHIN Program:  Revenue & Expenses": "Physician FTE ",
    "Budget": 0,
    "Budget Adjustments": 0,
    "Total": 0,
    "YTD Actual": 0,
    "Q4 Forecast": 0,
    "Q4 $ Forecast Variance to Budget": 0,
    "Q4 % Forecast Variance to Budget": 0,
    "Comments\nExplanations are required where \nthe Q4 Forecasted % exceeds +/-10%": null
  },
  "104": {
    "LHIN Program:  Revenue & Expenses": "Salaries (Worked hours + Benefit hours cost) - Physician",
    "Budget": 113000,
    "Budget Adjustments": 0,
    "Total": 113000,
    "YTD Actual": 82505,
    "Q4 Forecast": 113000,
    "Q4 $ Forecast Variance to Budget": 0,
    "Q4 % Forecast Variance to Budget": 0,
    "Comments\nExplanations are required where \nthe Q4 Forecasted % exceeds +/-10%": null
  },
  "105": {
    "LHIN Program:  Revenue & Expenses": "Benefit Contributions - Physician",
    "Budget": 0,
    "Budget Adjustments": 0,
    "Total": 0,
    "YTD Actual": 0,
    "Q4 Forecast": 0,
    "Q4 $ Forecast Variance to Budget": 0,
    "Q4 % Forecast Variance to Budget": 0,
    "Comments\nExplanations are required where \nthe Q4 Forecasted % exceeds +/-10%": null
  },
  "106": {
    "LHIN Program:  Revenue & Expenses": "Physician Assistant FTE ",
    "Budget": 0,
    "Budget Adjustments": 0,
    "Total": 0,
    "YTD Actual": 0,
    "Q4 Forecast": 0,
    "Q4 $ Forecast Variance to Budget": 0,
    "Q4 % Forecast Variance to Budget": 0,
    "Comments\nExplanations are required where \nthe Q4 Forecasted % exceeds +/-10%": null
  },
  "107": {
    "LHIN Program:  Revenue & Expenses": "Salaries (Worked hours + Benefit hours cost) - Physician Assist",
    "Budget": 0,
    "Budget Adjustments": 0,
    "Total": 0,
    "YTD Actual": 0,
    "Q4 Forecast": 0,
    "Q4 $ Forecast Variance to Budget": 0,
    "Q4 % Forecast Variance to Budget": 0,
    "Comments\nExplanations are required where \nthe Q4 Forecasted % exceeds +/-10%": null
  },
  "108": {
    "LHIN Program:  Revenue & Expenses": "Benefit Contributions - Physician Assist",
    "Budget": 0,
    "Budget Adjustments": 0,
    "Total": 0,
    "YTD Actual": 0,
    "Q4 Forecast": 0,
    "Q4 $ Forecast Variance to Budget": 0,
    "Q4 % Forecast Variance to Budget": 0,
    "Comments\nExplanations are required where \nthe Q4 Forecasted % exceeds +/-10%": null
  },
  "109": {
    "LHIN Program:  Revenue & Expenses": "NP FTE",
    "Budget": 1,
    "Budget Adjustments": 0,
    "Total": 1,
    "YTD Actual": 0.52,
    "Q4 Forecast": 0.75,
    "Q4 $ Forecast Variance to Budget": 0.25,
    "Q4 % Forecast Variance to Budget": 0.25,
    "Comments\nExplanations are required where \nthe Q4 Forecasted % exceeds +/-10%": "Partial vacancy during year"
  },
  "110": {
    "LHIN Program:  Revenue & Expenses": "Salaries (Worked hours + Benefit hours cost) - NP",
    "Budget": 119520,
    "Budget Adjustments": 0,
    "Total": 119520,
    "YTD Actual": 46697,
    "Q4 Forecast": 82000,
    "Q4 $ Forecast Variance to Budget": 37520,
    "Q4 % Forecast Variance to Budget": 0.3139223561,
    "Comments\nExplanations are required where \nthe Q4 Forecasted % exceeds +/-10%": "Partial vacancy during year"
  },
  "111": {
    "LHIN Program:  Revenue & Expenses": "Benefit Contributions - NP",
    "Budget": 23501,
    "Budget Adjustments": 0,
    "Total": 23501,
    "YTD Actual": 9182,
    "Q4 Forecast": 16303,
    "Q4 $ Forecast Variance to Budget": 7198,
    "Q4 % Forecast Variance to Budget": 0.3062848389,
    "Comments\nExplanations are required where \nthe Q4 Forecasted % exceeds +/-10%": "Partial vacancy during year"
  },
  "112": {
    "LHIN Program:  Revenue & Expenses": "Physiotherapist FTE ",
    "Budget": 0,
    "Budget Adjustments": 0,
    "Total": 0,
    "YTD Actual": 0,
    "Q4 Forecast": 0,
    "Q4 $ Forecast Variance to Budget": 0,
    "Q4 % Forecast Variance to Budget": 0,
    "Comments\nExplanations are required where \nthe Q4 Forecasted % exceeds +/-10%": null
  },
  "113": {
    "LHIN Program:  Revenue & Expenses": "Salaries (Worked hours + Benefit hours cost) - Physician Assist",
    "Budget": 0,
    "Budget Adjustments": 0,
    "Total": 0,
    "YTD Actual": 0,
    "Q4 Forecast": 0,
    "Q4 $ Forecast Variance to Budget": 0,
    "Q4 % Forecast Variance to Budget": 0,
    "Comments\nExplanations are required where \nthe Q4 Forecasted % exceeds +/-10%": null
  },
  "114": {
    "LHIN Program:  Revenue & Expenses": "Benefit Contributions - Physician Assist",
    "Budget": 0,
    "Budget Adjustments": 0,
    "Total": 0,
    "YTD Actual": 0,
    "Q4 Forecast": 0,
    "Q4 $ Forecast Variance to Budget": 0,
    "Q4 % Forecast Variance to Budget": 0,
    "Comments\nExplanations are required where \nthe Q4 Forecasted % exceeds +/-10%": null
  },
  "115": {
    "LHIN Program:  Revenue & Expenses": "Chiropractor FTE",
    "Budget": 0,
    "Budget Adjustments": 0,
    "Total": 0,
    "YTD Actual": 0,
    "Q4 Forecast": 0,
    "Q4 $ Forecast Variance to Budget": 0,
    "Q4 % Forecast Variance to Budget": 0,
    "Comments\nExplanations are required where \nthe Q4 Forecasted % exceeds +/-10%": null
  },
  "116": {
    "LHIN Program:  Revenue & Expenses": "Salaries (Worked hours + Benefit hours cost) - Chiropractor",
    "Budget": 0,
    "Budget Adjustments": 0,
    "Total": 0,
    "YTD Actual": 0,
    "Q4 Forecast": 0,
    "Q4 $ Forecast Variance to Budget": 0,
    "Q4 % Forecast Variance to Budget": 0,
    "Comments\nExplanations are required where \nthe Q4 Forecasted % exceeds +/-10%": null
  },
  "117": {
    "LHIN Program:  Revenue & Expenses": "Benefit Contributions - NP",
    "Budget": 0,
    "Budget Adjustments": 0,
    "Total": 0,
    "YTD Actual": 0,
    "Q4 Forecast": 0,
    "Q4 $ Forecast Variance to Budget": 0,
    "Q4 % Forecast Variance to Budget": 0,
    "Comments\nExplanations are required where \nthe Q4 Forecasted % exceeds +/-10%": null
  },
  "118": {
    "LHIN Program:  Revenue & Expenses": "All Other Medical Staff FTE",
    "Budget": 0,
    "Budget Adjustments": 0,
    "Total": 0,
    "YTD Actual": 0,
    "Q4 Forecast": 0,
    "Q4 $ Forecast Variance to Budget": 0,
    "Q4 % Forecast Variance to Budget": 0,
    "Comments\nExplanations are required where \nthe Q4 Forecasted % exceeds +/-10%": null
  },
  "119": {
    "LHIN Program:  Revenue & Expenses": "Salaries (Worked hours + Benefit hours cost) - Other Med",
    "Budget": 0,
    "Budget Adjustments": 0,
    "Total": 0,
    "YTD Actual": 0,
    "Q4 Forecast": 0,
    "Q4 $ Forecast Variance to Budget": 0,
    "Q4 % Forecast Variance to Budget": 0,
    "Comments\nExplanations are required where \nthe Q4 Forecasted % exceeds +/-10%": null
  },
  "120": {
    "LHIN Program:  Revenue & Expenses": "Benefit Contributions - Other Med",
    "Budget": 0,
    "Budget Adjustments": 0,
    "Total": 0,
    "YTD Actual": 0,
    "Q4 Forecast": 0,
    "Q4 $ Forecast Variance to Budget": 0,
    "Q4 % Forecast Variance to Budget": 0,
    "Comments\nExplanations are required where \nthe Q4 Forecasted % exceeds +/-10%": null
  },
  "121": {
    "LHIN Program:  Revenue & Expenses": "Total Compensation - Physician",
    "Budget": 113000,
    "Budget Adjustments": 0,
    "Total": 113000,
    "YTD Actual": 82505,
    "Q4 Forecast": 113000,
    "Q4 $ Forecast Variance to Budget": 0,
    "Q4 % Forecast Variance to Budget": 0,
    "Comments\nExplanations are required where \nthe Q4 Forecasted % exceeds +/-10%": null
  },
  "122": {
    "LHIN Program:  Revenue & Expenses": "Total Compensation - Physician Assistant",
    "Budget": 0,
    "Budget Adjustments": 0,
    "Total": 0,
    "YTD Actual": 0,
    "Q4 Forecast": 0,
    "Q4 $ Forecast Variance to Budget": 0,
    "Q4 % Forecast Variance to Budget": 0,
    "Comments\nExplanations are required where \nthe Q4 Forecasted % exceeds +/-10%": null
  },
  "123": {
    "LHIN Program:  Revenue & Expenses": "Total Compensation - NP",
    "Budget": 143021,
    "Budget Adjustments": 0,
    "Total": 143021,
    "YTD Actual": 55879,
    "Q4 Forecast": 98303,
    "Q4 $ Forecast Variance to Budget": 44718,
    "Q4 % Forecast Variance to Budget": 0.3126673705,
    "Comments\nExplanations are required where \nthe Q4 Forecasted % exceeds +/-10%": "Partial vacancy during year"
  },
  "124": {
    "LHIN Program:  Revenue & Expenses": "Total Compensation - Physiotherapists",
    "Budget": 0,
    "Budget Adjustments": 0,
    "Total": 0,
    "YTD Actual": 0,
    "Q4 Forecast": 0,
    "Q4 $ Forecast Variance to Budget": 0,
    "Q4 % Forecast Variance to Budget": 0,
    "Comments\nExplanations are required where \nthe Q4 Forecasted % exceeds +/-10%": null
  },
  "125": {
    "LHIN Program:  Revenue & Expenses": "Total Compensation - Chiropractors",
    "Budget": 0,
    "Budget Adjustments": 0,
    "Total": 0,
    "YTD Actual": 0,
    "Q4 Forecast": 0,
    "Q4 $ Forecast Variance to Budget": 0,
    "Q4 % Forecast Variance to Budget": 0,
    "Comments\nExplanations are required where \nthe Q4 Forecasted % exceeds +/-10%": null
  },
  "126": {
    "LHIN Program:  Revenue & Expenses": "Total Compensation - Other Medical Staff",
    "Budget": 0,
    "Budget Adjustments": 0,
    "Total": 0,
    "YTD Actual": 0,
    "Q4 Forecast": 0,
    "Q4 $ Forecast Variance to Budget": 0,
    "Q4 % Forecast Variance to Budget": 0,
    "Comments\nExplanations are required where \nthe Q4 Forecasted % exceeds +/-10%": null
  },
  "127": {
    "LHIN Program:  Revenue & Expenses": "Average Cost per FTE - Physician",
    "Budget": 0,
    "Budget Adjustments": 0,
    "Total": 0,
    "YTD Actual": 0,
    "Q4 Forecast": 0,
    "Q4 $ Forecast Variance to Budget": 0,
    "Q4 % Forecast Variance to Budget": 0,
    "Comments\nExplanations are required where \nthe Q4 Forecasted % exceeds +/-10%": null
  },
  "128": {
    "LHIN Program:  Revenue & Expenses": "Average Cost per FTE - Physician Assistant",
    "Budget": 0,
    "Budget Adjustments": 0,
    "Total": 0,
    "YTD Actual": 0,
    "Q4 Forecast": 0,
    "Q4 $ Forecast Variance to Budget": 0,
    "Q4 % Forecast Variance to Budget": 0,
    "Comments\nExplanations are required where \nthe Q4 Forecasted % exceeds +/-10%": null
  },
  "129": {
    "LHIN Program:  Revenue & Expenses": "Average Cost per FTE - NP",
    "Budget": 143021,
    "Budget Adjustments": 0,
    "Total": 143021,
    "YTD Actual": 107459.6153846154,
    "Q4 Forecast": 131070.6666666667,
    "Q4 $ Forecast Variance to Budget": 11950.3333333333,
    "Q4 % Forecast Variance to Budget": 0.083556494,
    "Comments\nExplanations are required where \nthe Q4 Forecasted % exceeds +/-10%": null
  },
  "130": {
    "LHIN Program:  Revenue & Expenses": "Average Cost per FTE - Physiotherapists",
    "Budget": 0,
    "Budget Adjustments": 0,
    "Total": 0,
    "YTD Actual": 0,
    "Q4 Forecast": 0,
    "Q4 $ Forecast Variance to Budget": 0,
    "Q4 % Forecast Variance to Budget": 0,
    "Comments\nExplanations are required where \nthe Q4 Forecasted % exceeds +/-10%": null
  },
  "131": {
    "LHIN Program:  Revenue & Expenses": "Average Cost per FTE - Chiropractor",
    "Budget": 0,
    "Budget Adjustments": 0,
    "Total": 0,
    "YTD Actual": 0,
    "Q4 Forecast": 0,
    "Q4 $ Forecast Variance to Budget": 0,
    "Q4 % Forecast Variance to Budget": 0,
    "Comments\nExplanations are required where \nthe Q4 Forecasted % exceeds +/-10%": null
  },
  "132": {
    "LHIN Program:  Revenue & Expenses": "Average Cost per FTE - Other Medical Staff",
    "Budget": 0,
    "Budget Adjustments": 0,
    "Total": 0,
    "YTD Actual": 0,
    "Q4 Forecast": 0,
    "Q4 $ Forecast Variance to Budget": 0,
    "Q4 % Forecast Variance to Budget": 0,
    "Comments\nExplanations are required where \nthe Q4 Forecasted % exceeds +/-10%": null
  },
  "133": {
    "LHIN Program:  Revenue & Expenses": "TOTAL PROGRAM FTE SUMMARY",
    "Budget": null,
    "Budget Adjustments": null,
    "Total": null,
    "YTD Actual": null,
    "Q4 Forecast": null,
    "Q4 $ Forecast Variance to Budget": null,
    "Q4 % Forecast Variance to Budget": null,
    "Comments\nExplanations are required where \nthe Q4 Forecasted % exceeds +/-10%": null
  },
  "134": {
    "LHIN Program:  Revenue & Expenses": "MOS FTE",
    "Budget": 4.52,
    "Budget Adjustments": 0,
    "Total": 4.52,
    "YTD Actual": 4.15,
    "Q4 Forecast": 4.3,
    "Q4 $ Forecast Variance to Budget": 0.22,
    "Q4 % Forecast Variance to Budget": 0.0486725664,
    "Comments\nExplanations are required where \nthe Q4 Forecasted % exceeds +/-10%": null
  },
  "135": {
    "LHIN Program:  Revenue & Expenses": "UPP  FTE",
    "Budget": 13.16,
    "Budget Adjustments": 0,
    "Total": 13.16,
    "YTD Actual": 13.89,
    "Q4 Forecast": 13.5,
    "Q4 $ Forecast Variance to Budget": -0.34,
    "Q4 % Forecast Variance to Budget": -0.0258358663,
    "Comments\nExplanations are required where \nthe Q4 Forecasted % exceeds +/-10%": null
  },
  "136": {
    "LHIN Program:  Revenue & Expenses": "Total FTE Physician, Physician Asst, NP, Physiotherapists, Chiropractor, Other Med Staff",
    "Budget": 1,
    "Budget Adjustments": 0,
    "Total": 1,
    "YTD Actual": 0.52,
    "Q4 Forecast": 0.75,
    "Q4 $ Forecast Variance to Budget": 0.25,
    "Q4 % Forecast Variance to Budget": 0.25,
    "Comments\nExplanations are required where \nthe Q4 Forecasted % exceeds +/-10%": "Partial vacancy during year"
  },
  "137": {
    "LHIN Program:  Revenue & Expenses": "Total FTE",
    "Budget": 18.68,
    "Budget Adjustments": 0,
    "Total": 18.68,
    "YTD Actual": 18.56,
    "Q4 Forecast": 18.55,
    "Q4 $ Forecast Variance to Budget": 0.13,
    "Q4 % Forecast Variance to Budget": 0.0069593148,
    "Comments\nExplanations are required where \nthe Q4 Forecasted % exceeds +/-10%": null
  },
  "138": {
    "LHIN Program:  Revenue & Expenses": "TOTAL PROGRAM FTE Compensation",
    "Budget": null,
    "Budget Adjustments": null,
    "Total": null,
    "YTD Actual": null,
    "Q4 Forecast": null,
    "Q4 $ Forecast Variance to Budget": null,
    "Q4 % Forecast Variance to Budget": null,
    "Comments\nExplanations are required where \nthe Q4 Forecasted % exceeds +/-10%": null
  },
  "139": {
    "LHIN Program:  Revenue & Expenses": "Worked hours Cost",
    "Budget": 1658472,
    "Budget Adjustments": 0,
    "Total": 1658472,
    "YTD Actual": 1222702,
    "Q4 Forecast": 1653000,
    "Q4 $ Forecast Variance to Budget": 5472,
    "Q4 % Forecast Variance to Budget": 0.0032994226,
    "Comments\nExplanations are required where \nthe Q4 Forecasted % exceeds +/-10%": null
  },
  "140": {
    "LHIN Program:  Revenue & Expenses": "Benefit hours cost (includes contributions)",
    "Budget": 394088,
    "Budget Adjustments": 0,
    "Total": 394088,
    "YTD Actual": 305878,
    "Q4 Forecast": 395903,
    "Q4 $ Forecast Variance to Budget": -1815,
    "Q4 % Forecast Variance to Budget": -0.0046055703,
    "Comments\nExplanations are required where \nthe Q4 Forecasted % exceeds +/-10%": null
  },
  "141": {
    "LHIN Program:  Revenue & Expenses": "Total Compensation",
    "Budget": 2052560,
    "Budget Adjustments": 0,
    "Total": 2052560,
    "YTD Actual": 1528580,
    "Q4 Forecast": 2048903,
    "Q4 $ Forecast Variance to Budget": 3657,
    "Q4 % Forecast Variance to Budget": 0.0017816775,
    "Comments\nExplanations are required where \nthe Q4 Forecasted % exceeds +/-10%": null
  },
  "142": {
    "LHIN Program:  Revenue & Expenses": "Average Cost Per FTE",
    "Budget": 109880.0856531049,
    "Budget Adjustments": 0,
    "Total": 109880.0856531049,
    "YTD Actual": 82358.8362068966,
    "Q4 Forecast": 110452.9919137466,
    "Q4 $ Forecast Variance to Budget": -572.9062606417,
    "Q4 % Forecast Variance to Budget": -0.0052139226,
    "Comments\nExplanations are required where \nthe Q4 Forecasted % exceeds +/-10%": null
  },
  "143": {
    "LHIN Program:  Revenue & Expenses": "TOTAL PROGRAM Volunteer Summary",
    "Budget": null,
    "Budget Adjustments": null,
    "Total": null,
    "YTD Actual": null,
    "Q4 Forecast": null,
    "Q4 $ Forecast Variance to Budget": null,
    "Q4 % Forecast Variance to Budget": null,
    "Comments\nExplanations are required where \nthe Q4 Forecasted % exceeds +/-10%": null
  },
  "144": {
    "LHIN Program:  Revenue & Expenses": "# of Volunteers",
    "Budget": 0,
    "Budget Adjustments": 0,
    "Total": 0,
    "YTD Actual": 0,
    "Q4 Forecast": 0,
    "Q4 $ Forecast Variance to Budget": 0,
    "Q4 % Forecast Variance to Budget": 0,
    "Comments\nExplanations are required where \nthe Q4 Forecasted % exceeds +/-10%": null
  },
  "145": {
    "LHIN Program:  Revenue & Expenses": "Volunteer Hours",
    "Budget": 0,
    "Budget Adjustments": 0,
    "Total": 0,
    "YTD Actual": 0,
    "Q4 Forecast": 0,
    "Q4 $ Forecast Variance to Budget": 0,
    "Q4 % Forecast Variance to Budget": 0,
    "Comments\nExplanations are required where \nthe Q4 Forecasted % exceeds +/-10%": null
  },
  "146": {
    "LHIN Program:  Revenue & Expenses": "VH as % of Total FTE",
    "Budget": 0,
    "Budget Adjustments": 0,
    "Total": 0,
    "YTD Actual": 0,
    "Q4 Forecast": 0,
    "Q4 $ Forecast Variance to Budget": 0,
    "Q4 % Forecast Variance to Budget": 0,
    "Comments\nExplanations are required where \nthe Q4 Forecasted % exceeds +/-10%": null
  }
}